{
  "timeZone": "America/Denver",
  "dependencies": {},
  "exceptionLogging": "STACKDRIVER",
  "oauthScopes": [
    "https://www.googleapis.com/auth/gmail.addons.current.message.readonly",
    "https://www.googleapis.com/auth/script.external_request"
  ],
  "addOns": {
    "common": {
      "name": "Podium Task Creator",
      "logoUrl": "https://www.gstatic.com/images/icons/material/system/1x/task_alt_black_48dp.png",
      "layoutProperties": {
        "primaryColor": "#4F46E5"
      }
    },
    "gmail": {
      "contextualTriggers": [
        {
          "unconditional": {},
          "onTriggerFunction": "onGmailMessage"
        }
      ]
    }
  }
}
